asreviewcontrib/visualization/__init__.py
asreviewcontrib/visualization/_version.py
asreviewcontrib/visualization/entrypoint.py
asreviewcontrib/visualization/plot.py
asreviewcontrib/visualization/plot_base.py
asreviewcontrib/visualization/plot_discovery.py
asreviewcontrib/visualization/plot_inclusions.py
asreviewcontrib/visualization/plot_limit.py
asreviewcontrib/visualization/plot_progression.py
asreviewcontrib/visualization/quick.py
asreview_visualization-0.4.1.dist-info/LICENSE
asreview_visualization-0.4.1.dist-info/METADATA
asreview_visualization-0.4.1.dist-info/WHEEL
asreview_visualization-0.4.1.dist-info/entry_points.txt
asreview_visualization-0.4.1.dist-info/top_level.txt
asreview_visualization-0.4.1.dist-info/RECORD
