Metadata-Version: 2.1
Name: asreview-visualization
Version: 0.4.1
Summary: Visualization tools for the ASReview project
Home-page: https://github.com/asreview/asreview-visualization
Author: Utrecht University
Author-email: asreview@uu.nl
License: UNKNOWN
Project-URL: Bug Reports, https://github.com/asreview/asreview-visualization/issues
Project-URL: Source, https://github.com/asreview/asreview-visualization
Keywords: asreview plot visualization
Platform: UNKNOWN
Classifier: Development Status :: 3 - Alpha
Classifier: License :: OSI Approved :: Apache Software License
Classifier: Programming Language :: Python :: 3.5
Classifier: Programming Language :: Python :: 3.6
Classifier: Programming Language :: Python :: 3.7
License-File: LICENSE
Requires-Dist: numpy
Requires-Dist: matplotlib
Requires-Dist: asreview
